
{"items":[{"name":"Introduction","href":"index.html","topicHref":"index.html"},{"name":"Design Philosophy","href":"DesignPhilosophy.html","topicHref":"DesignPhilosophy.html"},{"name":"Utilities","items":[{"name":"Random Generator","href":"RandomGenerator.html","topicHref":"RandomGenerator.html"},{"name":"Encoding","href":"Encoding.html","topicHref":"Encoding.html"},{"name":"Secure Memory","href":"SecureMemory.html","topicHref":"SecureMemory.html"},{"name":"SecureBigUnsignedInteger","href":"SecureBigUnsignedInteger.html","topicHref":"SecureBigUnsignedInteger.html"}]},{"name":"Symmetric Encryption","items":[{"name":"SecretBox","href":"SecretBox.html","topicHref":"SecretBox.html"},{"name":"SecretStream","href":"SecretStream.html","topicHref":"SecretStream.html"},{"name":"AEAD","href":"AEAD.html","topicHref":"AEAD.html"},{"name":"Stream Ciphers","href":"StreamCiphers.html","topicHref":"StreamCiphers.html"}]},{"name":"Key Management","items":[{"name":"Key Derivation","href":"KeyDerivation.html","topicHref":"KeyDerivation.html"},{"name":"Key Exchange","href":"KeyExchange.html","topicHref":"KeyExchange.html"}]},{"name":"Hashing & Authentication","items":[{"name":"MAC","href":"MAC.html","topicHref":"MAC.html"},{"name":"Hashing","href":"Hashing.html","topicHref":"Hashing.html"},{"name":"Dual-Phase Password Hashing","href":"DualPhasePasswordHashing.html","topicHref":"DualPhasePasswordHashing.html"}]},{"name":"Public Key Cryptography","href":"PublicKeyCrypto.html","topicHref":"PublicKeyCrypto.html"}],"pdf":false}
